{
  "gitSyncId": "69590eac6c1ae66fe697eb01_b7f43399-a6e4-48e9-ad4f-13fab1dac4f9",
  "id": "PlayerPollPage_PollAuth.logout",
  "pluginId": "js-plugin",
  "pluginType": "JS",
  "unpublishedAction": {
    "actionConfiguration": {
      "encodeParamsToggle": true,
      "jsArguments": [],
      "paginationType": "NONE",
      "timeoutInMillisecond": 10000
    },
    "collectionId": "PlayerPollPage_PollAuth",
    "confirmBeforeExecute": false,
    "datasource": {
      "isAutoGenerated": false,
      "name": "UNUSED_DATASOURCE",
      "pluginId": "js-plugin"
    },
    "dynamicBindingPathList": [
      {
        "key": "body"
      }
    ],
    "fullyQualifiedName": "PollAuth.logout",
    "name": "logout",
    "pageId": "PlayerPollPage",
    "runBehaviour": "AUTOMATIC",
    "userSetOnLoad": true
  }
}