{
  "gitSyncId": "694e5865c148916db7d99c87_588dfa7c-d8bd-4ee6-b85e-3c78d1d2d1a8",
  "id": "PlayerPollPage_PollAuth.sessionMaxAgeMs",
  "pluginId": "js-plugin",
  "pluginType": "JS",
  "unpublishedAction": {
    "actionConfiguration": {
      "encodeParamsToggle": true,
      "jsArguments": [],
      "paginationType": "NONE",
      "timeoutInMillisecond": 10000
    },
    "collectionId": "PlayerPollPage_PollAuth",
    "confirmBeforeExecute": false,
    "datasource": {
      "isAutoGenerated": false,
      "name": "UNUSED_DATASOURCE",
      "pluginId": "js-plugin"
    },
    "dynamicBindingPathList": [
      {
        "key": "body"
      }
    ],
    "fullyQualifiedName": "PollAuth.sessionMaxAgeMs",
    "name": "sessionMaxAgeMs",
    "pageId": "PlayerPollPage",
    "runBehaviour": "MANUAL",
    "userSetOnLoad": false
  }
}